nn_rsa/__init__.py
nn_rsa/example.py
nn_rsa/nn_rsa.py
nn_rsa-1.0.2.dist-info/METADATA
nn_rsa-1.0.2.dist-info/WHEEL
nn_rsa-1.0.2.dist-info/top_level.txt
nn_rsa-1.0.2.dist-info/zip-safe
nn_rsa-1.0.2.dist-info/RECORD
